yt_comment_dl/__init__.py
yt_comment_dl/cli.py
yt_comment_dl/comment_processor.py
yt_comment_dl/constants.py
yt_comment_dl/http_client.py
yt_comment_dl/models.py
yt_comment_dl/parser.py
yt_comment_dl/py.typed
yt_comment_dl/youtube_comment_downloader.py
yt_comment_dl-0.1.0.dist-info/WHEEL
yt_comment_dl-0.1.0.dist-info/entry_points.txt
yt_comment_dl-0.1.0.dist-info/METADATA
yt_comment_dl-0.1.0.dist-info/RECORD
