Metadata-Version: 2.3
Name: yt-comment-dl
Version: 0.1.0
Summary: Simple script for downloading Youtube comments without using the Youtube API
Keywords: youtube,comments,scraper,downloader,api-free
Author: egbertbouman, Jo. Adly
Author-email: egbertbouman <ebouman@gmail.com>, Jo. Adly <youssefadly237@gmail.com>
License: The MIT License (MIT)
Classifier: License :: OSI Approved :: MIT License
Classifier: Environment :: Console
Classifier: Operating System :: OS Independent
Classifier: Programming Language :: Python :: 3
Classifier: Programming Language :: Python :: 3.10
Classifier: Programming Language :: Python :: 3.11
Classifier: Programming Language :: Python :: 3.12
Requires-Dist: dateparser>=1.2.2
Requires-Dist: requests>=2.32.5
Requires-Python: >=3.10
Project-URL: Changelog, https://github.com/youssefadly237/yt-comment-dl/releases
Project-URL: Homepage, https://github.com/youssefadly237/yt-comment-dl
Project-URL: Issues, https://github.com/youssefadly237/yt-comment-dl/issues
Project-URL: Repository, https://github.com/youssefadly237/yt-comment-dl
